mimecast_api/__init__.py
mimecast_api/api_object.py
mimecast_api/errors.py
mimecast_api/post_rest.py
mimecast_api-0.5.dist-info/LICENSE
mimecast_api-0.5.dist-info/METADATA
mimecast_api-0.5.dist-info/WHEEL
mimecast_api-0.5.dist-info/top_level.txt
mimecast_api-0.5.dist-info/RECORD
