Metadata-Version: 2.1
Name: mimecast-api
Version: 0.5
Summary: Access Mimecast email security services
Home-page: https://gitlab.com/jaredjennings/python-mimecast_api
Author: Jared Jennings
Author-email: jjennings@fastmail.fm
License: BSD-2-Clause
Platform: UNKNOWN
Classifier: Development Status :: 3 - Alpha
Classifier: Intended Audience :: Information Technology
Classifier: Intended Audience :: Developers
Classifier: Intended Audience :: System Administrators
Classifier: License :: OSI Approved :: BSD License
Classifier: Operating System :: OS Independent
Classifier: Programming Language :: Python :: 3
Classifier: Topic :: Communications :: Email
Classifier: Topic :: Security
Requires-Dist: requests
